odoo/addons/crm_phone_extension/README.rst
odoo/addons/crm_phone_extension/__init__.py
odoo/addons/crm_phone_extension/__manifest__.py
odoo/addons/crm_phone_extension/i18n/crm_phone_extension.pot
odoo/addons/crm_phone_extension/i18n/es.po
odoo/addons/crm_phone_extension/i18n/it.po
odoo/addons/crm_phone_extension/models/__init__.py
odoo/addons/crm_phone_extension/models/crm_lead.py
odoo/addons/crm_phone_extension/readme/CONTRIBUTORS.rst
odoo/addons/crm_phone_extension/readme/DESCRIPTION.rst
odoo/addons/crm_phone_extension/static/description/icon.png
odoo/addons/crm_phone_extension/static/description/index.html
odoo/addons/crm_phone_extension/views/crm_lead_view.xml
odoo14_addon_crm_phone_extension-14.0.1.0.2.dev7.dist-info/METADATA
odoo14_addon_crm_phone_extension-14.0.1.0.2.dev7.dist-info/WHEEL
odoo14_addon_crm_phone_extension-14.0.1.0.2.dev7.dist-info/top_level.txt
odoo14_addon_crm_phone_extension-14.0.1.0.2.dev7.dist-info/RECORD
